learnit/__init__.py
learnit/definitions.py
learnit/autoconverter/__init__.py
learnit/autoconverter/autoconverter.py
learnit/autoconverter/autoconverter_hfu.py
learnit/autoconverter/text.py
learnit/autolearn/__init__.py
learnit/autolearn/autolearn.py
learnit/autolearn/blueprints.py
learnit/autolearn/evaluate.py
learnit/autolearn/functions.py
learnit/autopipeline/__init__.py
learnit/autopipeline/autopipeline.py
learnit/tests/__init__.py
learnit-0.0.0rc1.dist-info/LICENSE
learnit-0.0.0rc1.dist-info/METADATA
learnit-0.0.0rc1.dist-info/WHEEL
learnit-0.0.0rc1.dist-info/top_level.txt
learnit-0.0.0rc1.dist-info/RECORD
