Metadata-Version: 2.1
Name: learnit
Version: 0.0.0rc1
Summary: A Tool for Machine Learning Beginners
Home-page: https://github.com/megagonlabs/learnit
Author: Megagon Labs
Author-email: learnit@megagon.ai
License: Apache Software License (Apache License, Version 2.0)
Keywords: machine learning,automated machine learning,AutoML,feature extraction
Platform: UNKNOWN
Requires-Python: >=3.5
Requires-Dist: numpy (>=1.16.3)
Requires-Dist: pandas (>=0.22.0)
Requires-Dist: six (>=1.11.0)
Requires-Dist: scipy (>=0.19.1)
Requires-Dist: scikit-learn (>=0.22)
Requires-Dist: progressbar2
Requires-Dist: tabulate
Requires-Dist: matplotlib
Requires-Dist: gensim (==3.4.0)
